openstack_vim_driver/__init__.py
openstack_vim_driver/openstack_vim_driver.py
openstack_vim_driver/etc/configuration.ini
openstack_vim_driver-6.0.1.data/scripts/openstack-vim-driver
openstack_vim_driver-6.0.1.dist-info/METADATA
openstack_vim_driver-6.0.1.dist-info/RECORD
openstack_vim_driver-6.0.1.dist-info/WHEEL
openstack_vim_driver-6.0.1.dist-info/top_level.txt
tests/__init__.py
tests/test_vim_driver.py
