Metadata-Version: 2.1
Name: openstack-vim-driver
Version: 6.0.1
Summary: OpenStack VIM Driver for Open Baton
Home-page: https://github.com/openbaton/openstack-python-vim-driver
Author: Open Baton
Author-email: dev@openbaton.org
License: Apache 2
Platform: UNKNOWN
Classifier: Development Status :: 4 - Beta
Classifier: Intended Audience :: Developers
Classifier: Topic :: Software Development :: Build Tools
Classifier: Topic :: Utilities
Classifier: License :: OSI Approved :: Apache Software License
Requires-Dist: python-plugin-sdk
Requires-Dist: python-glanceclient
Requires-Dist: python-neutronclient
Requires-Dist: python-novaclient
Requires-Dist: requests
